randsecret/__init__.py
randsecret/generate.py
randsecret-1.0.0.dist-info/LICENSE
randsecret-1.0.0.dist-info/WHEEL
randsecret-1.0.0.dist-info/METADATA
randsecret-1.0.0.dist-info/RECORD
