Metadata-Version: 2.1
Name: randsecret
Version: 1.0.0
Summary: Generate a secret key
Author-email: Ben Brady <benbradybusiness@gmail.com>
Requires-Python: >=3.8
Classifier: Development Status :: 4 - Beta
Classifier: Intended Audience :: Developers
Classifier: Natural Language :: English
Classifier: Operating System :: OS Independent
Classifier: License :: OSI Approved :: MIT License
Classifier: Programming Language :: Python
Classifier: Programming Language :: Python :: 3.8
Classifier: Programming Language :: Python :: 3.9
Classifier: Programming Language :: Python :: 3.10
Classifier: Programming Language :: Python :: 3.11
Classifier: Typing :: Typed
Project-URL: Source, https://github.com/Ben-Brady/secretgen
